example_yunhu/__init__.py
example_yunhu/flask_demo.py
example_yunhu/set_board_demo.py
yunhu/__init__.py
yunhu/main.py
yunhu/openapi.py
yunhu/subscription.py
yunhu-0.0.7.dist-info/LICENSE.txt
yunhu-0.0.7.dist-info/METADATA
yunhu-0.0.7.dist-info/WHEEL
yunhu-0.0.7.dist-info/top_level.txt
yunhu-0.0.7.dist-info/RECORD
